pyfoldercheck/__init__.py
pyfoldercheck/configs.py
pyfoldercheck/main.py
pyfoldercheck/static.py
pyfoldercheck/utils.py
pyfoldercheck-0.0.6.dist-info/LICENSE
pyfoldercheck-0.0.6.dist-info/METADATA
pyfoldercheck-0.0.6.dist-info/WHEEL
pyfoldercheck-0.0.6.dist-info/entry_points.txt
pyfoldercheck-0.0.6.dist-info/top_level.txt
pyfoldercheck-0.0.6.dist-info/RECORD
