Metadata-Version: 2.1
Name: pyfoldercheck
Version: 0.0.6
Summary: Pyfoldercheck will apply a set of checks on files in a folder
Home-page: https://veltzer.github.io/pyfoldercheck
Download-URL: https://github.com/veltzer/pyfoldercheck
Author: Mark Veltzer
Author-email: mark.veltzer@gmail.com
Maintainer: Mark Veltzer
Maintainer-email: mark.veltzer@gmail.com
License: MIT
Keywords: mp3,pdf,collection
Platform: python3
Classifier: Development Status :: 4 - Beta
Classifier: Environment :: Console
Classifier: Operating System :: OS Independent
Classifier: Programming Language :: Python
Classifier: Programming Language :: Python :: 3
Classifier: Programming Language :: Python :: 3 :: Only
Classifier: Programming Language :: Python :: 3.11
Classifier: Topic :: Utilities
Classifier: License :: OSI Approved :: MIT License
License-File: LICENSE
Requires-Dist: pytconf
Requires-Dist: pylogconf
